odoo/addons/despatch_advice_import/README.rst
odoo/addons/despatch_advice_import/__init__.py
odoo/addons/despatch_advice_import/__manifest__.py
odoo/addons/despatch_advice_import/i18n/despatch_advice_import.pot
odoo/addons/despatch_advice_import/i18n/es.po
odoo/addons/despatch_advice_import/i18n/fr.po
odoo/addons/despatch_advice_import/i18n/it.po
odoo/addons/despatch_advice_import/readme/CONTRIBUTORS.rst
odoo/addons/despatch_advice_import/readme/CREDITS.rst
odoo/addons/despatch_advice_import/readme/DESCRIPTION.rst
odoo/addons/despatch_advice_import/security/ir.model.access.csv
odoo/addons/despatch_advice_import/static/description/icon.png
odoo/addons/despatch_advice_import/static/description/index.html
odoo/addons/despatch_advice_import/tests/__init__.py
odoo/addons/despatch_advice_import/tests/test_despatch_advice_import.py
odoo/addons/despatch_advice_import/wizard/__init__.py
odoo/addons/despatch_advice_import/wizard/despatch_advice_import.py
odoo/addons/despatch_advice_import/wizard/despatch_advice_import.xml
odoo_addon_despatch_advice_import-16.0.1.2.1.dist-info/METADATA
odoo_addon_despatch_advice_import-16.0.1.2.1.dist-info/WHEEL
odoo_addon_despatch_advice_import-16.0.1.2.1.dist-info/top_level.txt
odoo_addon_despatch_advice_import-16.0.1.2.1.dist-info/RECORD
