Metadata-Version: 2.1
Name: odoo-addon-despatch_advice_import
Version: 16.0.1.2.1
Summary: Despatch Advice import
Home-page: https://github.com/OCA/edi
Author: ACSONE SA/NV,BCIM,Odoo Community Association (OCA)
Author-email: support@odoo-community.org
License: AGPL-3
Classifier: Programming Language :: Python
Classifier: Framework :: Odoo
Classifier: Framework :: Odoo :: 16.0
Classifier: License :: OSI Approved :: GNU Affero General Public License v3
Requires-Python: >=3.10
Requires-Dist: odoo-addon-base-business-document-import<16.1dev,>=16.0dev
Requires-Dist: odoo<16.1dev,>=16.0a
